mender/__init__.py
mender/attribute.py
mender/device.py
mender/error.py
mender/group.py
mender/user.py
mender/user_new.py
mender/user_update.py
mender-0.0.5.dist-info/METADATA
mender-0.0.5.dist-info/WHEEL
mender-0.0.5.dist-info/top_level.txt
mender-0.0.5.dist-info/RECORD
