Metadata-Version: 2.1
Name: mender
Version: 0.0.5
Summary: Mender SDK for python
Home-page: https://github.com/yongjhih/mender-python
Author: Andrew Chen
Author-email: yongjhih@gmail.com
License: UNKNOWN
Project-URL: Bug Reports, https://github.com/FloTechnologies/flo-sdk-python/issues
Platform: UNKNOWN
Classifier: Development Status :: 3 - Alpha
Classifier: Intended Audience :: Developers
Classifier: License :: OSI Approved :: MIT License
Classifier: Programming Language :: Python :: 3.6
Requires-Dist: dataclasses
Requires-Dist: requests
Requires-Dist: jsonpickle
Requires-Dist: future-fstrings
Requires-Dist: aiohttp
Requires-Dist: jsontofu
